{"starttime":1576369302712,"GameName":"test","GuildId":"621429173570895872","saveTimer":5,"PCs":{"226766417918296064":{"Name":"Testy","High Concept":"Undefined","Trouble":["No Trouble","No description"],"In Peril":{"Boxes":true,"Current":0,"Maximum":1},"Doomed":{"Boxes":true,"Current":0,"Maximum":1},"Aspects":{},"Conditions":{},"Stunts":{},"Approaches":{"Forceful":0,"Sneaky":0,"Careful":0,"Quick":0,"Clever":0,"Flashy":0},"imgURL":"","NPC":true}},"NPCs":{"Testy 2":{"Name":"Testy 2","High Concept":"Undefined","Trouble":["No Trouble","No description"],"Stress":{"Boxes":true,"Current":0,"Maximum":6},"In Peril":{"Boxes":true,"Current":0,"Maximum":1},"Doomed":{"Boxes":true,"Current":0,"Maximum":1},"Aspects":{},"Conditions":{},"Stunts":{},"Approaches":{"Forceful":0,"Sneaky":0,"Careful":0,"Quick":0,"Clever":0,"Flashy":0},"imgURL":"","NPC":false}},"Log":[{"subject":"654800050211389469","spoiler":false,"logstr":"\"Game saved!\""}]}